extras_py/__init__.py
extras_py-0.1.4.dist-info/WHEEL
extras_py-0.1.4.dist-info/METADATA
extras_py-0.1.4.dist-info/RECORD
